{"id":"0f208e3c-54d7-4e24-954b-ed9ab921d3eb","urn":107916,"ukprn":10078386,"name":"Moortown Primary School","establishmentType":1,"establishmentGroup":4,"establishmentStatus":1,"establishmentPhase":2,"address":{"addressLine1":"Shadwell Lane","town":"Leeds","county":"West Yorkshire","postcode":"LS17 6DR"},"location":{"latitude":53.84489190000001,"longitude":-1.53257,"regionCode":"E12000003","localAuthorityCode":"383","districtAdministrativeCode":"E08000035","administrativeWardCode":"E05011405","parliamentaryConstituencyCode":"E14000779","msoaCode":"E02002352","lsoaCode":"E01011512"},"contact":{"website":"www.moortown.leeds.sch.uk/","telephone":"01132685915"},"minAge":5,"maxAge":11,"gender":3,"boarders":1,"officialSixthForm":2,"nurseryProvision":2,"childcareFacilities":0,"religiousCharacter":0,"admissionsPolicy":0,"schoolCapacity":210,"totalPupils":211,"totalBoys":112,"totalGirls":99,"specialClasses":2,"percentageFreeSchoolMeals":4.3,"trustSchool":0,"federationCode":16208,"furtherEducationType":0,"urbanRural":"A1","head":{"title":"Mr","firstName":"David","lastName":"Roundtree","jobTitle":"Headteacher"},"ofsted":{"rating":1,"lastInspectionDate":"2011-11-24T00:00:00.000Z"},"createdAt":"2024-03-12T19:44:05.133Z","updatedAt":"2024-03-15T15:18:23.219Z","type":"school","relationships":["f5432b96-7169-4457-8cbf-4e29f353ee98","f8a7e6f3-08c4-40d0-b8c8-da2503f81044"]}