{"id":"2c67abd7-e2f3-4b02-99f6-ab847b2d97f4","urn":107944,"ukprn":10072261,"name":"Swarcliffe Primary School","establishmentType":1,"establishmentGroup":4,"establishmentStatus":1,"establishmentPhase":2,"address":{"addressLine1":"Swarcliffe Drive","town":"Leeds","county":"West Yorkshire","postcode":"LS14 5JW"},"location":{"latitude":53.8214209,"longitude":-1.4510914,"regionCode":"E12000003","localAuthorityCode":"383","districtAdministrativeCode":"E08000035","administrativeWardCode":"E05011391","parliamentaryConstituencyCode":"E14000778","msoaCode":"E02002370","lsoaCode":"E01011724"},"contact":{"website":"www.swarcliffeprimary.co.uk/","telephone":"01132930275"},"minAge":3,"maxAge":11,"gender":3,"boarders":1,"officialSixthForm":2,"nurseryProvision":1,"childcareFacilities":0,"religiousCharacter":0,"admissionsPolicy":0,"schoolCapacity":315,"totalPupils":326,"totalBoys":154,"totalGirls":172,"specialClasses":2,"percentageFreeSchoolMeals":46.5,"trustSchool":0,"furtherEducationType":0,"urbanRural":"A1","head":{"firstName":"Debra","lastName":"Hill","jobTitle":"Headteacher"},"ofsted":{"rating":2,"lastInspectionDate":"2020-01-15T00:00:00.000Z"},"createdAt":"2024-03-12T19:44:05.137Z","updatedAt":"2023-09-06T13:14:34.833Z","type":"school"}