{"id":"2c6b13b5-1408-44cb-871e-dc68d4675844","urn":135935,"ukprn":10027710,"name":"Leeds West Academy","establishmentType":28,"establishmentGroup":10,"establishmentStatus":1,"establishmentPhase":4,"address":{"addressLine1":"Intake Lane","addressLine3":"Rodley","town":"Leeds","county":"West Yorkshire","postcode":"LS13 1DQ"},"location":{"latitude":53.8145726,"longitude":-1.6537268,"regionCode":"E12000003","localAuthorityCode":"383","districtAdministrativeCode":"E08000035","administrativeWardCode":"E05011387","parliamentaryConstituencyCode":"E14000781","msoaCode":"E02002381","lsoaCode":"E01011328"},"contact":{"website":"www.leedswestacademy.org.uk","telephone":"01132295454"},"minAge":11,"maxAge":16,"gender":3,"boarders":1,"officialSixthForm":2,"nurseryProvision":0,"childcareFacilities":0,"religiousCharacter":0,"admissionsPolicy":4,"schoolCapacity":1200,"totalPupils":1360,"totalBoys":633,"totalGirls":727,"specialClasses":0,"percentageFreeSchoolMeals":37.5,"trustSchool":3,"trustCode":5316,"schoolSponsorCode":3719,"furtherEducationType":0,"urbanRural":"A1","head":{"title":"Mr","firstName":"Dan","lastName":"Whieldon","jobTitle":"Principal"},"ofsted":{"rating":2,"lastInspectionDate":"2019-05-14T23:00:00.000Z"},"createdAt":"2024-03-12T19:44:05.170Z","updatedAt":"2024-03-15T15:18:23.635Z","type":"school","relationships":["0dcaf4b8-b01f-442e-98e5-fa59d7db1024","2fcdc527-f475-4919-b6c5-1a2dea3011b1","9c11c00c-4d14-497e-b157-e0b59e958cba","c3038716-0187-411a-ad4b-f88066bc7d09","c68e18a8-2e33-4136-854d-c809613967eb","f8a7e6f3-08c4-40d0-b8c8-da2503f81044"]}