{"id":"c652a601-1200-4818-b7c9-11e1cf17e9e9","urn":107860,"ukprn":10069031,"name":"Horsforth Newlaithes Primary School","establishmentType":1,"establishmentGroup":4,"establishmentStatus":1,"establishmentPhase":2,"address":{"addressLine1":"Victoria Crescent","addressLine2":"Horsforth","town":"Leeds","county":"West Yorkshire","postcode":"LS18 4PT"},"location":{"latitude":53.8290887,"longitude":-1.6446889,"regionCode":"E12000003","localAuthorityCode":"383","districtAdministrativeCode":"E08000035","administrativeWardCode":"E05011547","parliamentaryConstituencyCode":"E14000886","msoaCode":"E02002356","lsoaCode":"E01011454"},"contact":{"website":"www.newlaithes.co.uk/","telephone":"01132588645"},"minAge":4,"maxAge":11,"gender":3,"boarders":1,"officialSixthForm":2,"nurseryProvision":2,"childcareFacilities":0,"religiousCharacter":0,"admissionsPolicy":0,"schoolCapacity":420,"totalPupils":421,"totalBoys":227,"totalGirls":194,"specialClasses":2,"percentageFreeSchoolMeals":3.3,"trustSchool":0,"furtherEducationType":0,"urbanRural":"A1","head":{"title":"Mrs","firstName":"Joanne","lastName":"Blacoe","jobTitle":"Headteacher"},"ofsted":{"rating":2,"lastInspectionDate":"2022-06-08T23:00:00.000Z"},"createdAt":"2024-03-12T19:44:05.116Z","updatedAt":"2023-09-06T13:14:34.833Z","type":"school"}